wirepas_backend_client/__about__.py
wirepas_backend_client/__init__.py
wirepas_backend_client/__main__.py
wirepas_backend_client/api/__init__.py
wirepas_backend_client/api/mqtt/__init__.py
wirepas_backend_client/api/mqtt/connectors.py
wirepas_backend_client/api/mqtt/decorators.py
wirepas_backend_client/api/mqtt/handlers.py
wirepas_backend_client/api/mqtt/mqtt_options.py
wirepas_backend_client/api/mqtt/settings.py
wirepas_backend_client/api/mqtt/topics.py
wirepas_backend_client/api/stream/__init__.py
wirepas_backend_client/api/stream/stream.py
wirepas_backend_client/api/wnt/__init__.py
wirepas_backend_client/api/wnt/__main__.py
wirepas_backend_client/api/wnt/connectors.py
wirepas_backend_client/api/wnt/handlers.py
wirepas_backend_client/api/wnt/settings.py
wirepas_backend_client/api/wnt/manager/__init__.py
wirepas_backend_client/api/wnt/manager/authentication.py
wirepas_backend_client/api/wnt/manager/manager.py
wirepas_backend_client/api/wnt/manager/metadata.py
wirepas_backend_client/api/wnt/manager/realtime.py
wirepas_backend_client/api/wpe/__init__.py
wirepas_backend_client/api/wpe/__main__.py
wirepas_backend_client/api/wpe/connectors.py
wirepas_backend_client/api/wpe/settings.py
wirepas_backend_client/cli/__init__.py
wirepas_backend_client/cli/cli_starter.py
wirepas_backend_client/cli/gateway.py
wirepas_backend_client/cli/shell.py
wirepas_backend_client/management/__init__.py
wirepas_backend_client/management/daemon.py
wirepas_backend_client/management/inventory.py
wirepas_backend_client/mesh/__init__.py
wirepas_backend_client/mesh/device.py
wirepas_backend_client/mesh/gateway.py
wirepas_backend_client/mesh/network.py
wirepas_backend_client/mesh/sink.py
wirepas_backend_client/mesh/state.py
wirepas_backend_client/mesh/interfaces/__init__.py
wirepas_backend_client/mesh/interfaces/beacon.py
wirepas_backend_client/mesh/interfaces/mqtt.py
wirepas_backend_client/mesh/interfaces/remote_api.py
wirepas_backend_client/mesh/set_diagnostics/__init__.py
wirepas_backend_client-1.3.7.dist-info/LICENSE
wirepas_backend_client-1.3.7.dist-info/METADATA
wirepas_backend_client-1.3.7.dist-info/WHEEL
wirepas_backend_client-1.3.7.dist-info/entry_points.txt
wirepas_backend_client-1.3.7.dist-info/top_level.txt
wirepas_backend_client-1.3.7.dist-info/RECORD
