Metadata-Version: 2.1
Name: wirepas-backend-client
Version: 1.3.7
Summary: Interfaces to interact with Wirepas backend services.
Home-page: https://github.com/wirepas/backend-client
Author: Wirepas Ltd
Author-email: opensource@wirepas.com
License: Apache-2
Keywords: wirepas connectivity iot mesh
Platform: UNKNOWN
Classifier: Development Status :: 4 - Beta
Classifier: Intended Audience :: Developers
Classifier: License :: OSI Approved :: Apache Software License
Classifier: Topic :: Software Development :: Libraries
Classifier: Programming Language :: Python :: 3
Requires-Dist: PyYAML (==5.3)
Requires-Dist: cbor2 (==4.1.2)
Requires-Dist: fluent-logger (==0.9.4)
Requires-Dist: paho-mqtt (==1.5.0)
Requires-Dist: pandas (==0.25.3)
Requires-Dist: pycryptodome (==3.9.4)
Requires-Dist: websocket-client (==0.48.0)
Requires-Dist: wirepas-messaging (==1.3.0)
